jinja2_ext_custom_autoescaping/__init__.py
jinja2_ext_custom_autoescaping/ext.py
jinja2_ext_custom_autoescaping-0.1.0.dist-info/LICENSE
jinja2_ext_custom_autoescaping-0.1.0.dist-info/WHEEL
jinja2_ext_custom_autoescaping-0.1.0.dist-info/METADATA
jinja2_ext_custom_autoescaping-0.1.0.dist-info/RECORD
